{
  "anchor": {
    "anchor_age_seconds": null,
    "local_timestamp": "11/10/2025, 6:37:33 AM",
    "price": 3589.9,
    "product": "ETH-USD",
    "server_timestamps": [
      null,
      null,
      null
    ],
    "used": "last_trade",
    "venue": "Coinbase Advanced Trade REST"
  },
  "clock": {
    "checked_epoch": 1762778255,
    "fresh": false,
    "fresh_reason": "local_timestamp age 1762778255s > 900",
    "ts_ct": "2025-11-10T06:37:35-06:00"
  },
  "cross_check": {
    "discrepancy": {
      "diff_pct": 0,
      "level": "none"
    },
    "price": 3589.9,
    "product": "ETH-USD",
    "server_timestamp": "2025-11-10T12:37:34.667073555Z",
    "venue": "Coinbase Exchange public ticker"
  },
  "ratios": {
    "eth_btc": null
  }
}
