{
  "anchor": {
    "anchor_age_seconds": null,
    "local_timestamp": "1/19/2026, 9:24:21 AM",
    "price": 3214.2,
    "product": "ETH-USD",
    "server_timestamps": [
      null,
      null,
      null
    ],
    "used": "last_trade",
    "venue": "Coinbase Advanced Trade REST"
  },
  "clock": {
    "checked_epoch": 1768836263,
    "fresh": false,
    "fresh_reason": "local_timestamp age 1768836263s > 900",
    "ts_ct": "2026-01-19T09:24:23-06:00"
  },
  "cross_check": {
    "discrepancy": {
      "diff_pct": 0.0003111198915984728,
      "level": "none"
    },
    "price": 3214.19,
    "product": "ETH-USD",
    "server_timestamp": "2026-01-19T15:24:20.567724047Z",
    "venue": "Coinbase Exchange public ticker"
  },
  "ratios": {
    "eth_btc": null
  }
}
