{
  "anchor": {
    "anchor_age_seconds": null,
    "local_timestamp": "1/22/2026, 4:25:20 AM",
    "price": 3002.68,
    "product": "ETH-USD",
    "server_timestamps": [
      null,
      null,
      null
    ],
    "used": "last_trade",
    "venue": "Coinbase Advanced Trade REST"
  },
  "clock": {
    "checked_epoch": 1769077523,
    "fresh": false,
    "fresh_reason": "local_timestamp age 1769077523s > 900",
    "ts_ct": "2026-01-22T04:25:23-06:00"
  },
  "cross_check": {
    "discrepancy": {
      "diff_pct": 0,
      "level": "none"
    },
    "price": 3002.68,
    "product": "ETH-USD",
    "server_timestamp": "2026-01-22T10:25:19.790569950Z",
    "venue": "Coinbase Exchange public ticker"
  },
  "ratios": {
    "eth_btc": null
  }
}
