{
  "anchor": {
    "anchor_age_seconds": null,
    "local_timestamp": "5/30/2026, 2:39:46 AM",
    "price": 2011.44,
    "product": "ETH-USD",
    "server_timestamps": [
      null,
      null,
      null
    ],
    "used": "last_trade",
    "venue": "Coinbase Advanced Trade REST"
  },
  "clock": {
    "checked_epoch": 1780126788,
    "fresh": false,
    "fresh_reason": "local_timestamp age 1780126788s > 900",
    "ts_ct": "2026-05-30T02:39:48-05:00"
  },
  "cross_check": {
    "discrepancy": {
      "diff_pct": 0.0009943174756258885,
      "level": "none"
    },
    "price": 2011.42,
    "product": "ETH-USD",
    "server_timestamp": "2026-05-30T07:39:46.251551327Z",
    "venue": "Coinbase Exchange public ticker"
  },
  "ratios": {
    "eth_btc": null
  }
}
