{
  "anchor": {
    "anchor_age_seconds": null,
    "local_timestamp": "1/16/2026, 7:25:34 PM",
    "price": 3291.63,
    "product": "ETH-USD",
    "server_timestamps": [
      null,
      null,
      null
    ],
    "used": "last_trade",
    "venue": "Coinbase Advanced Trade REST"
  },
  "clock": {
    "checked_epoch": 1768613136,
    "fresh": false,
    "fresh_reason": "local_timestamp age 1768613136s > 900",
    "ts_ct": "2026-01-16T19:25:36-06:00"
  },
  "cross_check": {
    "discrepancy": {
      "diff_pct": 0.01002593070258767,
      "level": "none"
    },
    "price": 3291.3,
    "product": "ETH-USD",
    "server_timestamp": "2026-01-17T01:25:35.706133299Z",
    "venue": "Coinbase Exchange public ticker"
  },
  "ratios": {
    "eth_btc": null
  }
}
