{
  "anchor": {
    "anchor_age_seconds": null,
    "local_timestamp": "5/17/2026, 6:03:19 AM",
    "price": 2190.33,
    "product": "ETH-USD",
    "server_timestamps": [
      null,
      null,
      null
    ],
    "used": "last_trade",
    "venue": "Coinbase Advanced Trade REST"
  },
  "clock": {
    "checked_epoch": 1779015802,
    "fresh": false,
    "fresh_reason": "local_timestamp age 1779015802s > 900",
    "ts_ct": "2026-05-17T06:03:22-05:00"
  },
  "cross_check": {
    "discrepancy": {
      "diff_pct": 0,
      "level": "none"
    },
    "price": 2190.33,
    "product": "ETH-USD",
    "server_timestamp": "2026-05-17T11:03:11.852731697Z",
    "venue": "Coinbase Exchange public ticker"
  },
  "ratios": {
    "eth_btc": null
  }
}
