{
  "anchor": {
    "anchor_age_seconds": null,
    "local_timestamp": "3/4/2026, 4:28:32 PM",
    "price": 2157.15,
    "product": "ETH-USD",
    "server_timestamps": [
      null,
      null,
      null
    ],
    "used": "last_trade",
    "venue": "Coinbase Advanced Trade REST"
  },
  "clock": {
    "checked_epoch": 1772663315,
    "fresh": false,
    "fresh_reason": "local_timestamp age 1772663315s > 900",
    "ts_ct": "2026-03-04T16:28:35-06:00"
  },
  "cross_check": {
    "discrepancy": {
      "diff_pct": 0,
      "level": "none"
    },
    "price": 2157.15,
    "product": "ETH-USD",
    "server_timestamp": "2026-03-04T22:28:34.660929997Z",
    "venue": "Coinbase Exchange public ticker"
  },
  "ratios": {
    "eth_btc": null
  }
}
