{
  "anchor": {
    "anchor_age_seconds": null,
    "local_timestamp": "12/19/2025, 6:37:53 AM",
    "price": 2954.63,
    "product": "ETH-USD",
    "server_timestamps": [
      null,
      null,
      null
    ],
    "used": "last_trade",
    "venue": "Coinbase Advanced Trade REST"
  },
  "clock": {
    "checked_epoch": 1766147875,
    "fresh": false,
    "fresh_reason": "local_timestamp age 1766147875s > 900",
    "ts_ct": "2025-12-19T06:37:55-06:00"
  },
  "cross_check": {
    "discrepancy": {
      "diff_pct": 0.008461654321113012,
      "level": "none"
    },
    "price": 2954.38,
    "product": "ETH-USD",
    "server_timestamp": "2025-12-19T12:37:55.098292636Z",
    "venue": "Coinbase Exchange public ticker"
  },
  "ratios": {
    "eth_btc": null
  }
}
