{
  "anchor": {
    "anchor_age_seconds": null,
    "local_timestamp": "1/4/2026, 6:37:02 AM",
    "price": 3138.63,
    "product": "ETH-USD",
    "server_timestamps": [
      null,
      null,
      null
    ],
    "used": "last_trade",
    "venue": "Coinbase Advanced Trade REST"
  },
  "clock": {
    "checked_epoch": 1767530224,
    "fresh": false,
    "fresh_reason": "local_timestamp age 1767530224s > 900",
    "ts_ct": "2026-01-04T06:37:04-06:00"
  },
  "cross_check": {
    "discrepancy": {
      "diff_pct": 0,
      "level": "none"
    },
    "price": 3138.63,
    "product": "ETH-USD",
    "server_timestamp": "2026-01-04T12:37:01.268655786Z",
    "venue": "Coinbase Exchange public ticker"
  },
  "ratios": {
    "eth_btc": null
  }
}
