{
  "anchor": {
    "anchor_age_seconds": null,
    "local_timestamp": "2/13/2026, 10:08:48 PM",
    "price": 2052.7,
    "product": "ETH-USD",
    "server_timestamps": [
      null,
      null,
      null
    ],
    "used": "last_trade",
    "venue": "Coinbase Advanced Trade REST"
  },
  "clock": {
    "checked_epoch": 1771042130,
    "fresh": false,
    "fresh_reason": "local_timestamp age 1771042130s > 900",
    "ts_ct": "2026-02-13T22:08:50-06:00"
  },
  "cross_check": {
    "discrepancy": {
      "diff_pct": 0.0034100845944636657,
      "level": "none"
    },
    "price": 2052.77,
    "product": "ETH-USD",
    "server_timestamp": "2026-02-14T04:08:47.774135807Z",
    "venue": "Coinbase Exchange public ticker"
  },
  "ratios": {
    "eth_btc": null
  }
}
